instVirt/__init__.py
instVirt/Eletricidade/décima
instVirt/Eletricidade/nona
instVirt/Eletricidade/oitava
instVirt/Eletricidade/primeira
instVirt/Eletricidade/quarta
instVirt/Eletricidade/quinta
instVirt/Eletricidade/segunda
instVirt/Eletricidade/sexta
instVirt/Eletricidade/sétima
instVirt/Eletricidade/terceira
instVirt/Matemática/décima
instVirt/Matemática/nona
instVirt/Matemática/oitava
instVirt/Matemática/primeira
instVirt/Matemática/quarta
instVirt/Matemática/quinta
instVirt/Matemática/segunda
instVirt/Matemática/sexta
instVirt/Matemática/sétima
instVirt/Matemática/terceira
instVirt/Sistemas-Operacionais/décima
instVirt/Sistemas-Operacionais/nona
instVirt/Sistemas-Operacionais/oitava
instVirt/Sistemas-Operacionais/primeira
instVirt/Sistemas-Operacionais/quarta
instVirt/Sistemas-Operacionais/quinta
instVirt/Sistemas-Operacionais/segunda
instVirt/Sistemas-Operacionais/sexta
instVirt/Sistemas-Operacionais/sétima
instVirt/Sistemas-Operacionais/terceira
instVirt/Tecnologia-da-Informação/décima
instVirt/Tecnologia-da-Informação/nona
instVirt/Tecnologia-da-Informação/oitava
instVirt/Tecnologia-da-Informação/primeira
instVirt/Tecnologia-da-Informação/quarta
instVirt/Tecnologia-da-Informação/quinta
instVirt/Tecnologia-da-Informação/segunda
instVirt/Tecnologia-da-Informação/sexta
instVirt/Tecnologia-da-Informação/sétima
instVirt/Tecnologia-da-Informação/terceira
instVirt-1.1a8.dist-info/LICENSE
instVirt-1.1a8.dist-info/WHEEL
instVirt-1.1a8.dist-info/METADATA
instVirt-1.1a8.dist-info/RECORD
