Metadata-Version: 2.1
Name: instVirt
Version: 1.1a8
Summary: instVirt, este projeto constroi um instrutor virtual para auxílio em
Home-page: https://github.com/asl-sl/instVirt
License: UNKNOWN
Author: Leonardo de Araújo Lima
Author-email: leonardo@asl-sl.com.br
Classifier: License :: OSI Approved :: GNU General Public License v3 or later (GPLv3+)
